polygon_contains_point.cpython-310-x86_64-linux-gnu.so
polygon_contains_point-1.1.dist-info/top_level.txt
polygon_contains_point-1.1.dist-info/RECORD
polygon_contains_point-1.1.dist-info/WHEEL
polygon_contains_point-1.1.dist-info/METADATA
polygon_contains_point-1.1.dist-info/LICENSE
